langchain_advertools/__init__.py
langchain_advertools/website_loader.py
langchain_advertools-0.0.3.dist-info/METADATA
langchain_advertools-0.0.3.dist-info/WHEEL
langchain_advertools-0.0.3.dist-info/RECORD
