Metadata-Version: 2.4
Name: langchain-advertools
Version: 0.0.3
Summary: LangChain integration for advertools
Author-email: Elias Dabbas <eliasdabbas@gmail.com>
Requires-Python: >=3.10
Requires-Dist: advertools>=0.14.0
Requires-Dist: langchain>=0.3.0
